alu.v
module alu (
    input [31:0] op1,
    input [31:0] op2,
    input [2:0] func3,
    input [6:0] func7,
    output reg [31:0] add_result,
    output reg [31:0] sub_result,
    output reg [31:0] xor_result,
    output reg [31:0] or_result,
    output reg [31:0] and_result,
    output reg [31:0] shift_left_result,
    output reg [31:0] shift_right_result,
    output reg [31:0] signed_shift_right_result,
    output reg [31:0] signed_compare_result,
    output reg [31:0] unsigned_compare_result,
    output reg func7_result,
    output reg [31:0] addsub_result,
    output reg [31:0] srlsra_result,
    output reg [31:0] out
);

    // Suma
    always @* begin
        add_result = op1 + op2;
        sub_result = op1 - op2;
        xor_result = op1 ^ op2;
        or_result = op1 | op2;
        and_result = op1 & op2;
        shift_left_result = op1 << (op2[5:0]);
        shift_right_result = op1 >> (op2[5:0]);
        signed_shift_right_result = (op1) >>> (op2[5:0]);
        signed_compare_result = ($signed(op1) < $signed(op2)) ? 1 : 0;
        unsigned_compare_result = (op1 < op2) ? 1 : 0;
        func7_result = (func7 == 7'h20) ? 1 : 0;
        if (func7_result) begin
            addsub_result = sub_result;
            srlsra_result = signed_shift_right_result;
        end
        else begin
            addsub_result = add_result;
            srlsra_result = shift_right_result;
        end
        case (func3)
            3'b000: out = addsub_result;
            3'b001: out = shift_left_result;
            3'b010: out = signed_compare_result;
            3'b011: out = unsigned_compare_result;
            3'b100: out = xor_result;
            3'b101: out = srlsra_result;
            3'b110: out = or_result;
            3'b111: out = and_result;
        endcase
    end

endmodule

alu_tb.v
`include "alu.v"
`timescale 1ns / 1ps

module alu_tb;

    // Parámetros de prueba
    reg [31:0] op1_tb;
    reg [31:0] op2_tb;
    reg [2:0] func3_tb;
    reg [6:0] func7_tb;

    // Salidas de la ALU
    wire [31:0] add_result;
    wire [31:0] sub_result;
    wire [31:0] xor_result;
    wire [31:0] or_result;
    wire [31:0] and_result;
    wire [31:0] shift_left_result;
    wire [31:0] shift_right_result;
    wire [31:0] signed_shift_right_result;
    wire [31:0] signed_compare_result;
    wire [31:0] unsigned_compare_result;
    wire func7_result;
    wire [31:0] addsub_result;
    wire [31:0] srlsra_result;
    wire [31:0] out;

    // Instancia del módulo bajo prueba
    alu dut (
        .op1(op1_tb),
        .op2(op2_tb),
        .func3(func3_tb),
        .func7(func7_tb),
        .add_result(add_result),
        .sub_result(sub_result),
        .xor_result(xor_result),
        .or_result(or_result),
        .and_result(and_result),
        .shift_left_result(shift_left_result),
        .shift_right_result(shift_right_result),
        .signed_shift_right_result(signed_shift_right_result),
        .signed_compare_result(signed_compare_result),
        .unsigned_compare_result(unsigned_compare_result),
        .func7_result(func7_result),
        .addsub_result(addsub_result),
        .srlsra_result(srlsra_result),
        .out(out)
    );

    // Inicialización de la simulación
    initial begin
        $dumpfile("alu_tb.vcd");
        $dumpvars(0, alu_tb);
        // Asignación de valores a las entradas
        op1_tb = 32'h0000000A;
        op2_tb = 32'h00000005;
        func3_tb = 3'b0;
        func7_tb = 7'h0;

        // Esperar 10 unidades de tiempo
        #10;

        // Cambiar valores para probar otras operaciones
        op1_tb = 32'h0000000A;
        op2_tb = 32'h00000005;
        func3_tb = 3'b0;
        func7_tb = 7'h20;

        // Esperar 10 unidades de tiempo
        #10;

        // Cambiar valores para probar otras operaciones
        op1_tb = 32'hA;
        op2_tb = 32'h5;
        func3_tb = 3'b001;
        func7_tb = 7'h0;

        // Esperar 10 unidades de tiempo
        #10;

        // Cambiar valores para probar otras operaciones
        op1_tb = 32'hA;
        op2_tb = 32'h5;
        func3_tb = 3'b010;
        func7_tb = 7'h0;

        // Esperar 10 unidades de tiempo
        #10;

        // Cambiar valores para probar otras operaciones
        op1_tb = 32'hA;
        op2_tb = 32'h5;
        func3_tb = 3'b011;
        func7_tb = 7'h0;

        // Esperar 10 unidades de tiempo
        #10;

        // Cambiar valores para probar otras operaciones
        op1_tb = 32'hA;
        op2_tb = 32'h5;
        func3_tb = 3'b100;
        func7_tb = 7'h0;

        // Esperar 10 unidades de tiempo
        #10;

        // Cambiar valores para probar otras operaciones
        op1_tb = 32'hA;
        op2_tb = 32'h5;
        func3_tb = 3'b101;
        func7_tb = 7'h0;

        // Esperar 10 unidades de tiempo
        #10;

        // Cambiar valores para probar otras operaciones
        op1_tb = 32'hA;
        op2_tb = 32'h5;
        func3_tb = 3'b110;
        func7_tb = 7'h0;

        // Esperar 10 unidades de tiempo
        #10;

        // Cambiar valores para probar otras operaciones
        op1_tb = 32'hA;
        op2_tb = 32'h5;
        func3_tb = 3'b111;
        func7_tb = 7'h0;

        // Esperar 10 unidades de tiempo
        #10;

        // Cambiar valores para probar otras operaciones
        op1_tb = 32'hA;
        op2_tb = 32'h5;
        func3_tb = 3'b101;
        func7_tb = 7'h20;

        // Esperar 10 unidades de tiempo
        #10;

        // Terminar la simulación
        $finish;
    end

endmodule

alu_tb.vcd
$date
	Sat May 11 19:02:31 2024
$end
$version
	Icarus Verilog
$end
$timescale
	1ps
$end
$scope module alu_tb $end
$var wire 32 ! xor_result [31:0] $end
$var wire 32 " unsigned_compare_result [31:0] $end
$var wire 32 # sub_result [31:0] $end
$var wire 32 $ srlsra_result [31:0] $end
$var wire 32 % signed_shift_right_result [31:0] $end
$var wire 32 & signed_compare_result [31:0] $end
$var wire 32 ' shift_right_result [31:0] $end
$var wire 32 ( shift_left_result [31:0] $end
$var wire 32 ) out [31:0] $end
$var wire 32 * or_result [31:0] $end
$var wire 1 + func7_result $end
$var wire 32 , and_result [31:0] $end
$var wire 32 - addsub_result [31:0] $end
$var wire 32 . add_result [31:0] $end
$var reg 3 / func3_tb [2:0] $end
$var reg 7 0 func7_tb [6:0] $end
$var reg 32 1 op1_tb [31:0] $end
$var reg 32 2 op2_tb [31:0] $end
$scope module dut $end
$var wire 3 3 func3 [2:0] $end
$var wire 7 4 func7 [6:0] $end
$var wire 32 5 op1 [31:0] $end
$var wire 32 6 op2 [31:0] $end
$var reg 32 7 add_result [31:0] $end
$var reg 32 8 addsub_result [31:0] $end
$var reg 32 9 and_result [31:0] $end
$var reg 1 + func7_result $end
$var reg 32 : or_result [31:0] $end
$var reg 32 ; out [31:0] $end
$var reg 32 < shift_left_result [31:0] $end
$var reg 32 = shift_right_result [31:0] $end
$var reg 32 > signed_compare_result [31:0] $end
$var reg 32 ? signed_shift_right_result [31:0] $end
$var reg 32 @ srlsra_result [31:0] $end
$var reg 32 A sub_result [31:0] $end
$var reg 32 B unsigned_compare_result [31:0] $end
$var reg 32 C xor_result [31:0] $end
$upscope $end
$upscope $end
$enddefinitions $end
$comment Show the parameter values. $end
$dumpall
$end
#0
$dumpvars
b1111 C
b0 B
b101 A
b0 @
b0 ?
b0 >
b0 =
b101000000 <
b1111 ;
b1111 :
b0 9
b1111 8
b1111 7
b101 6
b1010 5
b0 4
b0 3
b101 2
b1010 1
b0 0
b0 /
b1111 .
b1111 -
b0 ,
0+
b1111 *
b1111 )
b101000000 (
b0 '
b0 &
b0 %
b0 $
b101 #
b0 "
b1111 !
$end
#10000
b101 )
b101 ;
b101 -
b101 8
1+
b100000 0
b100000 4
#20000
b101000000 )
b101000000 ;
b1111 -
b1111 8
0+
b0 0
b0 4
b1 /
b1 3
#30000
b0 )
b0 ;
b10 /
b10 3
#40000
b11 /
b11 3
#50000
b1111 )
b1111 ;
b100 /
b100 3
#60000
b0 )
b0 ;
b101 /
b101 3
#70000
b1111 )
b1111 ;
b110 /
b110 3
#80000
b0 )
b0 ;
b111 /
b111 3
#90000
b101 -
b101 8
1+
b100000 0
b100000 4
b101 /
b101 3
